dora_vggt/__init__.py
dora_vggt/__main__.py
dora_vggt/main.py
dora_vggt-0.0.0.dist-info/METADATA
dora_vggt-0.0.0.dist-info/WHEEL
dora_vggt-0.0.0.dist-info/entry_points.txt
dora_vggt-0.0.0.dist-info/top_level.txt
dora_vggt-0.0.0.dist-info/RECORD
