Metadata-Version: 2.4
Name: dora-vggt
Version: 0.0.0
Summary: dora-vggt
Author-email: Your Name <email@email.com>
License: MIT
Requires-Python: >=3.10
Requires-Dist: dora-rs>=0.3.9
Requires-Dist: torch>=2.7.0
Requires-Dist: torchvision>=0.22.0
Requires-Dist: vggt
